humpack/__init__.py
humpack/_lib_info.py
humpack/basic_containers.py
humpack/common.py
humpack/errors.py
humpack/hashing.py
humpack/packing.py
humpack/secure.py
humpack/transactions.py
humpack/utils.py
humpack/wrappers.py
humpack-0.1.1.dist-info/LICENSE
humpack-0.1.1.dist-info/METADATA
humpack-0.1.1.dist-info/WHEEL
humpack-0.1.1.dist-info/top_level.txt
humpack-0.1.1.dist-info/RECORD
