Metadata-Version: 2.1
Name: humpack
Version: 0.1.1
Summary: Human Readable Object Serialization and more
Home-page: https://github.com/fleeb24/HumPack
Author: Felix Leeb
Author-email: felix.leeb@hotmail.com
License: GPL3
Platform: UNKNOWN
Requires-Dist: wrapt (==1.11.2)
Requires-Dist: cryptography (>=2.7)
Requires-Dist: numpy (>=1.1)
